{"a":"https://www.amazon.fr/s?k=%s","m":"https://www.google.com/maps/search/%s","yt":"https://www.youtube.com/results?search_query=%s","?":"https://duckduckgo.com/?q=%s","w":"https://de.wikipedia.org/w/index.php?search=%s","dcc":"https://www.dict.cc/?s=%s","k":"https://www.kaggle.com/search?q=%s","d":"https://www.merriam-webster.com/dictionary/%s","e":"https://www.etymonline.com/search?q=%s","tpb":"https://thepiratebay.org/search.php?q=%s","aw":"https://wiki.archlinux.org/index.php?search=%s","azl":"https://search.azlyrics.com/search.php?q=%s","h":"https://hoogle.haskell.org/?hoogle=%s","fren":"https://translate.google.com/?sl=fr&tl=en&text=%s","enfr":"https://translate.google.com/?sl=en&tl=fr&text=%s","ende":"https://translate.google.com/?sl=en&tl=de&text=%s","deen":"https://translate.google.com/?sl=de&tl=en&text=%s","frde":"https://translate.google.com/?sl=fr&tl=de&text=%s","defr":"https://translate.google.com/?sl=de&tl=fr&text=%s"}